textual/__init__.py
textual/__main__.py
textual/_animator.py
textual/_ansi_sequences.py
textual/_ansi_theme.py
textual/_arrange.py
textual/_binary_encode.py
textual/_border.py
textual/_box_drawing.py
textual/_callback.py
textual/_cells.py
textual/_color_constants.py
textual/_compat.py
textual/_compositor.py
textual/_context.py
textual/_debug.py
textual/_dispatch_key.py
textual/_doc.py
textual/_duration.py
textual/_easing.py
textual/_event_broker.py
textual/_extrema.py
textual/_files.py
textual/_immutable_sequence_view.py
textual/_import_app.py
textual/_keyboard_protocol.py
textual/_layout_resolve.py
textual/_line_split.py
textual/_log.py
textual/_loop.py
textual/_markup_playground.py
textual/_node_list.py
textual/_on.py
textual/_opacity.py
textual/_parser.py
textual/_partition.py
textual/_path.py
textual/_profile.py
textual/_queue.py
textual/_resolve.py
textual/_segment_tools.py
textual/_sleep.py
textual/_slug.py
textual/_spatial_map.py
textual/_styles_cache.py
textual/_text_area_theme.py
textual/_time.py
textual/_tree_sitter.py
textual/_two_way_dict.py
textual/_types.py
textual/_wait.py
textual/_widget_navigation.py
textual/_win_sleep.py
textual/_work_decorator.py
textual/_wrap.py
textual/_xterm_parser.py
textual/actions.py
textual/app.py
textual/await_complete.py
textual/await_remove.py
textual/binding.py
textual/box_model.py
textual/cache.py
textual/canvas.py
textual/case.py
textual/clock.py
textual/color.py
textual/command.py
textual/compose.py
textual/constants.py
textual/containers.py
textual/content.py
textual/coordinate.py
textual/css/__init__.py
textual/css/_error_tools.py
textual/css/_help_renderables.py
textual/css/_help_text.py
textual/css/_style_properties.py
textual/css/_styles_builder.py
textual/css/constants.py
textual/css/errors.py
textual/css/match.py
textual/css/model.py
textual/css/parse.py
textual/css/query.py
textual/css/scalar.py
textual/css/scalar_animation.py
textual/css/styles.py
textual/css/stylesheet.py
textual/css/tokenize.py
textual-6.9.0.dist-info/LICENSE
textual-6.9.0.dist-info/METADATA
textual-6.9.0.dist-info/WHEEL
textual-6.9.0.dist-info/RECORD
